NatanSumProject/__init__.py
NatanSumProject/sum.py
NatanSumProject-0.1.24.dist-info/METADATA
NatanSumProject-0.1.24.dist-info/WHEEL
NatanSumProject-0.1.24.dist-info/top_level.txt
NatanSumProject-0.1.24.dist-info/RECORD
