Metadata-Version: 2.1
Name: NatanSumProject
Version: 0.1.24
Summary: NatanSumProject project
Home-page: UNKNOWN
Author: 2niknatan
Author-email: <mail@neuralnine.com>
License: UNKNOWN
Platform: UNKNOWN
Classifier: Programming Language :: Python :: 3
Classifier: Operating System :: Unix
Classifier: Operating System :: MacOS :: MacOS X
Classifier: Operating System :: Microsoft :: Windows
